Fadex-0.1.5.dist-info/METADATA
Fadex-0.1.5.dist-info/WHEEL
fadex/__init__.py
fadex/fadex.cp310-win_amd64.pyd
Fadex-0.1.5.dist-info/RECORD
