Metadata-Version: 2.3
Name: Fadex
Version: 0.1.5
Classifier: Programming Language :: Python :: 3
Classifier: License :: OSI Approved :: MIT License
Classifier: Operating System :: OS Independent
Classifier: Topic :: Internet :: WWW/HTTP :: Site Management
Classifier: Topic :: Software Development :: Libraries :: Python Modules
Summary: A Powerful WebScraper With Unmatched Performance
Keywords: web scraping,scraper,async,performance
Home-Page: https://github.com/fahad-programmer/fadex
Author-email: Fahad <malikfahadnawaz@gmail.com>
License: MIT
Project-URL: Source Code, https://github.com/fahad-programmer/fadex
